[{"place_id": 39760730, "licence": "Data \u00a9 OpenStreetMap contributors, ODbL 1.0. https://osm.org/copyright", "osm_type": "node", "osm_id": 3058230638, "boundingbox": ["45.1942036", "45.2342036", "4.4117375", "4.4517375"], "lat": "45.2142036", "lon": "4.4317375", "display_name": "Giorec, Riotord, Yssingeaux, Haute-Loire, Auvergne-Rh\u00f4ne-Alpes, Metropolitan France, 43220, France", "class": "place", "type": "hamlet", "importance": 0.36, "icon": "https://nominatim.openstreetmap.org/ui/mapicons//poi_place_village.p.20.png", "geojson": {"type": "Point", "coordinates": [4.4317375, 45.2142036]}}]